{"id": "PF_189", "url": "https://pitchfork.com/reviews/albums/croatian-amor-isa/", "name": ["Isa"], "description": ["loke", "rahbek", "multitud", "long", "multipli", "decad", "ago", "danish", "produc", "sing", "black", "metal", "band", "call", "sexdrom", "name", "brutal", "nois", "label", "posh", "isol", "1998", "lyric", "glaswegian", "tweepop", "band", "bell", "sebastian", "anyth", "better", "posh", "isol", "oeuvr", "rang", "absurdist", "power", "electronicsperform", "art", "damien", "dubrovnik", "faith", "new", "wave", "lust", "youth", "guid", "rahbek", "dispar", "work", "inquiri", "constitut", "underground", "music", "today", "ambient", "electron", "project", "croatian", "amor", "gentlest", "answer", "isa", "name", "muslim", "arab", "word", "jesu", "cohes", "project", "date", "selfdescrib", "bubblegum", "industri", "trace", "sugar", "left", "let", "plenti", "light", "air", "underst", "electron", "collag", "spiritu", "akin", "gothic", "electron", "arca", "terror", "throb", "gristl", "rahbek", "fascin", "popwith", "dissect", "pop", "part", "refigur", "melod", "element", "truli", "2016", "rahbek", "said", "listen", "kany", "west", "808", "heartbreak", "time", "plane", "aircraft", "broke", "emerg", "land", "isa", "sound", "like", "pop", "activ", "deconstruct", "ad", "sleek", "autotun", "rattl", "nonlinear", "shape", "album", "feel", "like", "seri", "wave", "collect", "song", "crest", "rel", "banger", "hearttug", "point", "reflex", "blue", "minim", "club", "track", "dark", "cut", "come", "circuit", "muscular", "rhythm", "rahbek", "beat", "forward", "backward", "time", "air", "hiss", "balloon", "isa", "busili", "accru", "new", "idea", "turn", "slow", "palli", "hard", "discern", "calm", "seren", "disquiet", "just", "blank", "extrem", "present", "concret", "languag", "like", "guttur", "scream", "robot", "refrain", "angel", "meet", "againinvok", "afterlif", "necessarili", "impli", "death", "vocal", "appearfrom", "like", "danish", "synthesisphilosoph", "soho", "rezanejad", "htrk", "jonnin", "standishthey", "pretti", "unsettl", "typic", "spoken", "robot", "augment", "lyricmonologu", "bring", "existenti", "edg", "featherlight", "music", "especi", "alienlik", "voic", "autom", "recur", "enhanc", "photo", "reveal", "pictur", "bird", "caught", "midflight", "goe", "enhanc", "bird", "human", "face", "scream", "obliqu", "critiqu", "lace", "brutal", "make", "feel", "safe", "gentl", "appear", "make", "feel", "safe", "voic", "slowli", "inton", "alarm", "light", "clear", "comment", "illus", "safeti", "final", "track", "world", "cell", "entir", "album", "collaps", "isa", "end", "hope", "shake", "childlik", "voic", "proclaim", "static", "believ", "thing", "chang", "isa", "omin", "interstiti", "eden", "11", "eden", "12", "featur", "rahbek", "previou", "collabor", "vanguard", "noisemak", "puce", "mari", "yve", "tumor", "amid", "slash", "industri", "nois", "chill", "silenc", "artist", "turn", "offer", "similar", "surreal", "speech", "gaze", "black", "airplan", "pitchblack", "sky", "vomit", "bird", "paradisesinist", "appeal", "unknown", "unavoid", "end", "time", "interstiti", "isa", "dimension", "break", "fourth", "wall", "record", "teenag", "rahbek", "painter", "gave", "favor", "nois", "music", "disillus", "galleri", "did", "art", "mayb", "iron", "pois", "new", "music", "evok", "wideopen", "wall", "galleri", "space", "mayb", "proof", "creativ", "circleand", "past", "expect", "emerg", "new", "tell", "futur"], "date_published": ["2019-01-31T06:00:00"], "sentiment": 0.035803872053872046, "pptitle": ["isa"]}