{"id": "TG_197", "url": "https://www.theguardian.com/music/2018/nov/11/lil-peep-posthumous-album-come-over-when-youre-sober-pt-2-review", "name": ["Lil", "Peep:", "Come", "Over", "When", "You\u2019re", "Sober", "Pt", "2", "review", "\u2013", "honouring", "the", "rapper\u2019s", "legacy", "|", "Music", "|", "The", "Guardian"], "description": ["anybodi", "anybodi", "hear", "strike", "refrain", "artist", "come", "posthum", "album", "rapper", "lil", "peep", "feel", "especi", "harrow", "long", "islandrais", "gustav", "hr", "die", "year", "ago", "accident", "overdos", "age", "21", "followup", "august", "2017", "debut", "record", "produc", "smokeasac", "prior", "peep", "death", "mother", "sift", "materi", "curat", "work", "honour", "son", "memori", "come", "your", "sober", "pt", "2", "doe", "exactli", "poignant", "hear", "sing", "track", "tri", "suicid", "life", "beauti", "matteroffactli", "relat", "drug", "abus", "attempt", "sugarcoat", "legaci", "unfilt", "melod", "cinemat", "raw", "album", "moment", "feel", "littl", "cheesi", "that", "keep", "unconcern", "cool", "end", "uplift", "spike", "synth", "guitar", "finger", "peep", "say", "im", "gonna", "long", "record", "beli", "provid", "solac", "devast", "fan", "facebook", "twitter", "pinterest", "watch", "video", "lil", "peep", "topic", "lil", "peep", "observ", "pop", "rock", "album", "review", "share", "facebook", "share", "twitter", "share", "email", "share", "linkedin", "share", "pinterest", "share", "whatsapp", "share", "messeng", "reus", "content"], "date_published": ["2018-11-11T08:00:04+0000"], "sentiment": 0.09377530364372469, "pptitle": ["lil", "peep", "come", "your", "sober", "pt", "2", "review", "honour", "rapper", "legaci", "music", "guardian"]}