{"id": "TG_45", "url": "https://www.theguardian.com/music/2019/feb/23/little-simz-grey-area-review-uk-rap-maverick", "name": ["Little", "Simz:", "Grey", "Area", "review", "\u2013", "rap", "maverick", "finally", "finds", "her", "groove", "|", "Music", "|", "The", "Guardian"], "description": ["wait", "game", "long", "lone", "just", "ask", "littl", "simz", "25yearold", "rapper", "releas", "album", "drop", "grey", "area", "week", "prop", "kendrick", "lamar", "call", "illest", "do", "right", "tour", "lauryn", "hill", "na", "spot", "forbess", "prestigi", "30", "30", "list", "track", "gorillaz", "featur", "hit", "hbo", "tv", "insecur", "past", "year", "simz", "aka", "simbi", "ajikawo", "evad", "householdnam", "fame", "album", "2017", "still", "wonderland", "review", "posit", "didnt", "reach", "100", "star", "risen", "tandem", "grime", "renaiss", "translat", "kind", "accolad", "given", "stormzi", "skepta", "atop", "festiv", "bill", "like", "contemporari", "j", "hu", "aj", "tracey", "silenc", "surround", "littl", "simz", "said", "critic", "deafen", "that", "north", "london", "touch", "ahead", "time", "born", "nigerian", "parent", "islington", "simz", "star", "variou", "televis", "show", "releas", "whop", "ep", "album", "2015", "long", "cardi", "b", "chart", "bodak", "yellow", "stefflon", "don", "sashay", "soldout", "tour", "simz", "make", "weird", "narr", "hiphop", "bold", "concept", "still", "wonderland", "came", "graphic", "novel", "exhibit", "festiv", "triplethreat", "like", "kojey", "radic", "bounc", "forth", "blur", "boundari", "perform", "artist", "poet", "rapper", "tune", "trill", "trumpet", "uk", "jazz", "scene", "properli", "erupt", "sound", "popular", "import", "stress", "remain", "independ", "selfreleas", "record", "age", "101", "imprint", "mayb", "littl", "simz", "sound", "hit", "right", "note", "lot", "said", "fight", "occupi", "space", "male", "peer", "take", "room", "especi", "blokeheavi", "world", "rap", "women", "creat", "new", "path", "male", "counterpart", "given", "free", "pass", "establish", "one", "imag", "overtli", "sexualis", "simz", "approach", "explor", "area", "inbetween", "mix", "genr", "experiment", "peer", "uncertain", "effect", "music", "lump", "grime", "fact", "cast", "sound", "dubstep", "jazz", "downtempo", "hiphop", "neosoul", "review", "includ", "2015", "suggest", "undeni", "technic", "flair", "simz", "voic", "meant", "partli", "didnt", "quit", "fit", "current", "go", "music", "mayb", "simz", "didnt", "break", "femal", "mc", "use", "hard", "sell", "mayb", "wasnt", "grime", "grime", "fan", "grime", "say", "6", "music", "listen", "type", "like", "young", "father", "album", "brave", "huge", "scope", "certainli", "incompar", "time", "possibl", "just", "need", "bigger", "tune", "grey", "area", "abund", "swing", "groov", "bog", "selfconsci", "poetic", "concept", "feel", "like", "record", "showcas", "anchor", "product", "work", "simz", "childhood", "friend", "inflo", "timbaland", "missi", "give", "song", "glue", "need", "born", "alex", "baranowski", "produc", "film", "compos", "taken", "note", "work", "danger", "mous", "michael", "kiwanuka", "2016", "album", "love", "hate", "industri", "game", "tag", "kiwanuka", "appear", "grey", "area", "final", "track", "flower", "big", "chunki", "break", "fat", "funk", "dollop", "crackl", "soul", "touch", "cosmic", "jazz", "cinemat", "string", "reminisc", "adrian", "young", "work", "ghostfac", "killah", "lead", "tune", "101", "fm", "featur", "best", "instrument", "stormzi", "shut", "facebook", "twitter", "pinterest", "watch", "video", "selfish", "littl", "simz", "simz", "unlock", "new", "level", "versatil", "track", "soberingli", "humour", "song", "border", "feelgood", "offenc", "simz", "missi", "deadpan", "play", "bravado", "line", "im", "jayz", "bad", "day", "shakespear", "worst", "day", "delici", "graini", "quinci", "basslin", "boss", "holler", "megaphon", "like", "whoop", "bluesman", "take", "men", "distract", "simz", "said", "interview", "dislik", "refer", "femal", "mc", "gender", "inequ", "prove", "fertil", "ground", "venom", "spit", "dont", "wanna", "address", "im", "best", "mere", "fact", "ive", "got", "ovari", "taut", "horrorscor", "string", "men", "continu", "women", "credit", "dont", "like", "pussi", "power", "quit", "voic", "gener", "track", "inwardlook", "given", "time", "wound", "pleas", "croon", "jamaica", "chronixx", "choru", "bar", "survey", "gang", "crime", "gun", "violenc", "detach", "brillianc", "simz", "said", "make", "grey", "area", "like", "therapi", "dark", "spell", "question", "isol", "tri", "clich", "goe", "make", "way", "smidgen", "struggl", "alien", "question", "career", "path", "pepper", "track", "im", "selfish", "goe", "cleo", "sol", "sweetli", "sung", "choru", "selfish", "flower", "look", "27", "club", "dead", "star", "wonder", "real", "price", "fame", "megastardom", "end", "grey", "area", "set", "differ", "kind", "stall", "littl", "simz", "slowburn", "she", "slicker", "sound", "there", "tell", "topic", "rap", "observ", "album", "review", "share", "facebook", "share", "twitter", "share", "email", "share", "linkedin", "share", "pinterest", "share", "whatsapp", "share", "messeng", "reus", "content"], "date_published": ["2019-02-23T14:00:16+0000"], "sentiment": 0.07107607227288076, "pptitle": ["littl", "simz", "grey", "area", "review", "rap", "maverick", "final", "find", "groov", "music", "guardian"]}