{"id": "UN_73", "url": "https://www.uncut.co.uk/news/steve-earle-dukes-return-album-guy-clark-songs-108815", "name": ["Steve", "Earle", "&", "The", "Dukes", "return", "with", "an", "album", "of", "Guy", "Clark", "songs", "-", "Uncut"], "description": ["steve", "earl", "duke", "announc", "new", "album", "guy", "releas", "new", "west", "march", "29a", "sequel", "2009", "album", "town", "cover", "song", "town", "van", "zandt", "earl", "new", "effort", "compris", "16", "song", "songwrit", "mentor", "guy", "clarkord", "latest", "issu", "uncut", "onlin", "sent", "homeno", "way", "do", "record", "say", "earl", "didnt", "want", "run", "guy", "have", "town", "record", "himtown", "van", "zandt", "guy", "clark", "like", "kerouac", "allen", "ginsberg", "come", "mentor", "im", "glad", "ask", "town", "hed", "hand", "copi", "buri", "heart", "wound", "knee", "ask", "guy", "question", "hed", "piec", "paper", "teach", "diagram", "song", "goe", "town", "alltim", "great", "writer", "finish", "song", "year", "life", "guy", "cancer", "wrote", "song", "day", "die", "sick", "die", "realli", "year", "life", "ask", "write", "song", "grandkid", "said", "dont", "know", "time", "didnt", "cowrit", "got", "busi", "guy", "die", "late", "regret", "guy", "produc", "earl", "record", "longtim", "product", "partner", "ray", "kennedi", "duke", "record", "includ", "kelley", "looney", "bass", "chri", "masterson", "guitar", "eleanor", "whitmor", "fiddl", "mandolin", "ricki", "ray", "jackson", "pedal", "steel", "guitar", "brad", "pemberton", "drum", "percuss", "guy", "featur", "guest", "appear", "emmyl", "harri", "rodney", "crowel", "terri", "allen", "jerri", "jeff", "walker", "mickey", "raphael", "shawn", "camp", "verlon", "thompson", "gari", "nicholson", "photograph", "jim", "mcguir", "perus", "tracklist", "preorder", "album", "includ", "limit", "edit", "red", "vinyl", "version", "here1", "dublin", "blue", "2", "la", "freeway", "3", "texa", "1947", "4", "desperado", "wait", "train", "5", "rita", "ballou", "6", "ballad", "lavern", "captain", "flint", "7", "randal", "knife", "8", "love", "9", "old", "time", "feel", "10", "heartbrok", "11", "gunfight", "ballad", "12", "park", "lot", "13", "aint", "go", "14", "si", "draper", "15", "new", "cut", "road", "16", "old", "friendssubscrib", "uncut", "make", "huge", "save", "cover", "price", "click", "herelik", "facebook", "date", "latest", "news", "uncutth", "march", "2019", "issu", "uncut", "sale", "uk", "new", "order", "cover", "insid", "youll", "pete", "shelley", "rip", "massiv", "2019", "album", "preview", "sharon", "van", "etten", "mark", "knopfler", "paul", "simonon", "john", "martyn", "steve", "gunn", "15track", "cd", "showcas", "best", "month", "new", "music", "includ", "bruce", "springsteen", "william", "tyler", "dream", "syndicateuncut", "past", "present", "futur", "great", "music"], "date_published": ["2019-01-09T15:05:21+00:00", "2019-01-09T15:05:21+00:00"], "sentiment": 0.09143668831168832, "pptitle": ["steve", "earl", "duke", "return", "album", "guy", "clark", "song", "uncut"]}