{"id": "UN_77", "url": "https://www.uncut.co.uk/news/curtis-mayfields-early-solo-albums-remastered-new-box-set-109002", "name": ["Curtis", "Mayfield's", "early", "solo", "albums", "remastered", "for", "new", "box", "set", "-", "Uncut"], "description": ["curti", "mayfield", "solo", "album", "remast", "new", "box", "set", "keep", "releas", "rhino", "februari", "22the", "lp", "cd", "set", "includ", "curti", "1970", "root", "1971", "world", "1973", "sweet", "exorcist", "1974", "mayfield", "1972", "superfli", "soundtrack", "order", "latest", "issu", "uncut", "onlin", "sent", "hometh", "remast", "album", "avail", "digit", "preorder", "keep", "earli", "order", "includ", "1212", "printsubscrib", "uncut", "make", "huge", "save", "cover", "price", "click", "herelik", "facebook", "follow", "twitter", "date", "latest", "news", "uncutth", "march", "2019", "issu", "uncut", "sale", "uk", "leonard", "cohen", "cover", "insid", "youll", "david", "bowi", "bob", "marley", "yardbird", "lambchop", "jessica", "pratt", "crass", "neu", "sean", "ono", "lennon", "15track", "cd", "showcas", "best", "month", "new", "music", "includ", "cass", "mccomb", "sleaford", "mod", "julia", "jacklin", "royal", "truxuncut", "past", "present", "futur", "great", "music"], "date_published": ["2019-01-23T10:31:34+00:00", "2019-01-23T10:31:34+00:00"], "sentiment": 0.15988636363636366, "content": "Curtis Mayfield\u2019s first four solo albums have been remastered for a new box set, Keep On Keeping On, to be released by Rhino on February 22.The LP or CD set includes Curtis (1970), Roots (1971), Back To The World (1973) and Sweet Exorcist (1974) \u2013 though not Mayfield\u2019s 1972 Superfly soundtrack. Order the latest issue of Uncut online and have it sent to your home!The remastered albums will also be available digitally. You can pre-order Keep On Keeping On here, with early orders including a 12\u00d712 print.Subscribe to Uncut and make huge savings on the cover price \u2013 find out by clicking here!Like us on Facebook or follow us on Twitter to keep up to date with the latest news from Uncut.The March 2019 issue of Uncut is now on sale in the UK \u2013 with Leonard Cohen on the cover. Inside, you\u2019ll find David Bowie, Bob Marley, The Yardbirds, Lambchop, Jessica Pratt, Crass, Neu!, Sean Ono Lennon and much more. Our 15-track CD also showcases the best of the month\u2019s new music, including Cass McCombs, Sleaford Mods, Julia Jacklin and Royal Trux.Uncut: the past, present and future of great music.", "pptitle": ["curti", "mayfield", "earli", "solo", "album", "remast", "new", "box", "set", "uncut"]}