{"id": "PF_186", "url": "https://pitchfork.com/reviews/albums/jay-glass-dubs-epitaph/", "name": ["Epitaph"], "description": ["dimitri", "papadato", "better", "known", "jay", "glass", "dub", "make", "dub", "music", "outsid", "perspect", "greek", "produc", "discographi", "cassett", "amount", "seri", "ters", "statement", "discont", "2016", "releas", "new", "teeth", "old", "countri", "glimmer", "briefli", "plung", "noir", "dub", "abstract", "trace", "nativ", "countri", "histor", "timelin", "glori", "turmoil", "2018", "plegnic", "steep", "athenian", "nostalgia", "ennui", "interpol", "sampl", "lak", "greek", "mainstream", "pop", "papadato", "far", "kingston", "bristol", "preoccupi", "odd", "site", "specif", "work", "emphas", "selfdescrib", "counterfactu", "approach", "jamaican", "genr", "discuss", "local", "sound", "cultur", "adjac", "realli", "epitaph", "bill", "proper", "solo", "lp", "consider", "catalog", "albumlength", "releas", "stretch", "year", "papadato", "move", "away", "narrow", "definit", "genr", "he", "exclud", "word", "dub", "track", "titl", "choos", "instead", "puls", "genr", "heavi", "reverber", "directli", "vein", "showdonttel", "effort", "like", "papadato", "project", "epitaph", "bass", "incorpor", "trace", "archaic", "greek", "song", "punk", "rock", "choral", "music", "breakbeat", "sinist", "religi", "fervor", "help", "unifi", "10", "track", "heavi", "drum", "minorkey", "synth", "odd", "touch", "blare", "saxophon", "throw", "thing", "kilter", "purist", "dub", "music", "carv", "contour", "space", "steadi", "heartbeat", "epitaph", "maximalist", "nonconformist", "dub", "record", "abandon", "ship", "altogeth", "papatado", "make", "use", "vocal", "vari", "degre", "success", "open", "seikilo", "consol", "begin", "extraterrestri", "religi", "chant", "mood", "quickli", "broken", "violent", "hammer", "shout", "titl", "element", "song", "come", "seikilo", "epitaph", "oldest", "known", "music", "composit", "papadato", "incant", "infus", "music", "mystic", "charg", "struggl", "hold", "qualiti", "new", "model", "emul", "come", "muddl", "flatten", "distort", "half", "epitaph", "caught", "murki", "undertow", "second", "half", "ascend", "higher", "vantag", "point", "synth", "descend", "firmament", "pierc", "hollow", "percuss", "intro", "gain", "strength", "clang", "cymbal", "laid", "drum", "machin", "mimic", "factori", "assembl", "line", "gleam", "synth", "melodi", "emerg", "clamor", "papadato", "vocal", "reenter", "benefitor", "there", "psychedel", "new", "calm", "croon", "rise", "like", "dissip", "mist", "lowend", "echo", "reson", "twang", "lest", "forget", "dubcontrarian", "root", "reckless", "toy", "dizzi", "matrix", "disembodi", "incant", "throati", "drone", "sound", "like", "sliver", "glass", "harp", "tyrann", "reverb", "track", "careen", "anxious", "bold", "climax", "conclud", "abrupt", "cliffhang", "frequent", "twist", "turn", "make", "grip", "listen", "theyr", "album", "main", "stumbl", "block", "recent", "interview", "papadato", "said", "work", "epitaph", "cours", "year", "larg", "collect", "projectsand", "show", "call", "melt", "pot", "influenc", "display", "impress", "rang", "transgress", "dub", "music", "epitaph", "quit", "settl", "final", "place", "rest"], "date_published": ["2019-01-30T06:00:00"], "sentiment": 0.06507873218399535, "pptitle": ["epitaph"]}