{"id": "RS_146", "url": "https://www.rollingstone.com/music/music-album-reviews/review-sumacs-free-metal-breaks-ugly-new-ground-727869/", "name": ["Review:", "Sumac\u2019s", "\u2018Love", "in", "Shadow\u2019", "and", "Their", "Collab", "With", "Keiji", "Haino", "\u2013", "Rolling", "Stone"], "description": ["sumac", "love", "shadow", "12", "keiji", "haino", "sumac", "american", "dollar", "face", "sideway", "your", "hideou", "look", "face", "sumac", "extrem", "metal", "power", "trio", "seemingli", "boundari", "jazzlik", "interplay", "hanker", "nois", "brittl", "extrem", "spars", "overwhelm", "leader", "aaron", "turner", "isi", "stress", "interview", "heavi", "mean", "lot", "just", "riff", "bludgeon", "sumac", "bigtent", "vision", "patient", "satisfi", "reminisc", "labelm", "tortois", "did", "rock", "music", "just", "replac", "vinylcollector", "obsess", "krautrock", "dub", "minim", "burlier", "slab", "swan", "free", "fusion", "jazz", "american", "japanes", "nois", "underground", "collag", "owe", "frenet", "cutandpast", "mr", "bungl", "nake", "citi", "like", "sludg", "band", "embark", "longform", "journey", "electr", "mile", "davi", "longest", "album", "sumac", "stretch", "massiv", "uglyscap", "cross", "12minut", "mark", "multipl", "chapter", "21minut", "open", "task", "play", "like", "tortois", "avantsampl", "platter", "djed", "suit", "link", "multipl", "idea", "cinemat", "there", "blacken", "mastodon", "pummel", "mathi", "turnaround", "stoogesesqu", "free", "nois", "doom", "stomp", "itchi", "mosquito", "drone", "end", "rhythm", "section", "slowli", "urp", "114", "ostanato", "turner", "provid", "bluesi", "noisefleck", "guitar", "solo", "that", "like", "frisel", "mark", "ribot", "say", "kirk", "hammett", "arc", "silver", "start", "amrepstyl", "sludg", "riff", "turner", "wheedl", "explor", "crackl", "stay", "silent", "share", "churn", "tumult", "void", "there", "paus", "coda", "sound", "like", "59second", "grindcor", "hsker", "d", "closer", "ecstasi", "unbecom", "recal", "scum", "tape", "wolf", "eye", "primit", "guitar", "avantblu", "orcutt", "turner", "old", "band", "isi", "recent", "output", "sige", "record", "label", "run", "turner", "musicalmarriag", "partner", "faith", "coloccia", "feel", "like", "decent", "hint", "watch", "sumac", "current", "obsess", "year", "theyv", "releas", "music", "freerock", "duo", "black", "spiritu", "japanes", "catastroph", "noisemet", "group", "endon", "harsh", "nois", "veteran", "daniel", "mench", "who", "idea", "rock", "isnt", "depend", "thing", "like", "melodi", "lyric", "rhythm", "song", "sumac", "collabor", "japanes", "avantgard", "icon", "keiji", "haino", "mayb", "2018", "best", "rock", "record", "66minut", "run", "time", "mix", "fragil", "chao", "deliveri", "raw", "viscer", "shock", "aggress", "free", "metal", "record", "press", "releas", "describ", "unrehears", "complet", "nonpremedit", "session", "flighti", "feedbacki", "churn", "pushpul", "rhythm", "familiar", "who", "caught", "haino", "decad", "solo", "consort", "extrem", "artist", "like", "saxophon", "multil", "peter", "brtzmann", "sludg", "band", "bori", "free", "music", "bedrock", "derek", "bailey", "nois", "thought", "leader", "merzbow", "jazz", "provocateur", "john", "zorn", "german", "orchestra", "zeitkratz", "sumac", "heft", "chop", "make", "feel", "like", "new", "territori", "especi", "explos", "hardhit", "drum", "nick", "yacyshyn", "play", "jazz", "skitter", "zeppelin", "muscl", "isnt", "jangleskre", "sonic", "youth", "psychedel", "blurt", "butthol", "surfer", "exact", "weaponsgrad", "militarytrain", "merciless"], "date_published": ["2018-09-24T14:08:15+00:00"], "sentiment": 0.06914564193975958, "pptitle": ["review", "sumac", "love", "shadow", "collab", "keiji", "haino", "roll", "stone"]}