{"id": "TG_30", "url": "https://www.theguardian.com/music/2019/mar/08/foals-everything-not-saved-will-be-lost-part-1-album-review", "name": ["Foals:", "Everything", "Not", "Saved", "Will", "Be", "Lost", "Part", "1", "review", "\u2013", "epic", "songs", "for", "a", "world", "in", "a", "spin", "|", "Music", "|", "The", "Guardian"], "description": ["band", "chemistri", "delic", "thing", "departur", "cofound", "bassist", "walter", "gerver", "major", "spanner", "work", "oxford", "foal", "replac", "rejig", "sound", "opt", "analogu", "synthesiserdriven", "bass", "line", "given", "groov", "differ", "zip", "2015", "drive", "distortionriffheavi", "went", "foal", "fifth", "way", "closer", "math", "rock", "debut", "antidot", "hardli", "away", "bristl", "busi", "angular", "rhythm", "abound", "fed", "lusher", "textur", "blend", "timbal", "clatter", "cowbel", "marimba", "recal", "like", "tom", "tom", "club", "tear", "fear", "philip", "glass", "ryuichi", "sakamoto", "enorm", "exit", "sonic", "dextrou", "driven", "stadiums", "chant", "choru", "power", "lament", "postglob", "warm", "environ", "bird", "left", "fli", "facebook", "twitter", "pinterest", "foal", "save", "lost", "1", "album", "artwork", "burn", "issu", "time", "climat", "chang", "polit", "uncertainti", "mental", "health", "problem", "abound", "music", "foal", "push", "creat", "fit", "soundtrack", "degre", "rollick", "juxtaposit", "silki", "ooh", "ooh", "urgent", "chant", "line", "talk", "head", "circa", "hous", "motion", "white", "onion", "coupl", "airi", "percuss", "claustrophob", "cri", "air", "contrast", "syrup", "suddenli", "shift", "gear", "pfunk", "fat", "groov", "sound", "like", "foal", "channel", "door", "la", "woman", "restless", "yearn", "yanni", "philippaki", "conjur", "best", "jim", "morrison", "howl", "frontman", "sung", "better", "reach", "drawer", "stun", "close", "doublewhammi", "sunday", "im", "world", "epic", "sweep", "song", "rebirth", "friendship", "flame", "juxtapos", "seren", "melancholi", "piano", "startl", "imageri", "dead", "fox", "burn", "hedg", "sleep", "daughter", "quest", "make", "sens", "planet", "panic", "amount", "foal", "finest", "there", "2", "follow", "later", "year", "topic", "foal", "pop", "rock", "indi", "album", "review", "share", "facebook", "share", "twitter", "share", "email", "share", "linkedin", "share", "pinterest", "share", "whatsapp", "share", "messeng", "reus", "content"], "date_published": ["2019-03-08T09:30:41+0000"], "sentiment": 0.10022401433691756, "pptitle": ["foal", "save", "lost", "1", "review", "epic", "song", "world", "spin", "music", "guardian"]}