{"id": "UN_94", "url": "https://www.uncut.co.uk/news/hear-title-track-royal-truxs-new-album-white-stuff-108775", "name": ["Hear", "the", "title", "track", "from", "Royal", "Trux's", "new", "album,", "White", "Stuff", "-", "Uncut"], "description": ["reform", "2015", "royal", "trux", "announc", "album", "new", "materi", "2000white", "stuff", "releas", "fat", "possum", "march", "1", "hear", "titl", "track", "beloword", "latest", "issu", "uncut", "onlin", "sent", "homenoth", "chang", "truxian", "univers", "creat", "teenag", "trux", "way", "life", "live", "separ", "say", "band", "jennif", "herrema", "hobbi", "rock", "kick", "long", "game", "lifer", "fear", "regret", "plenti", "gratitud", "way", "univers", "reward", "singular", "dynamiccheck", "white", "stuff", "tracklist", "look", "review", "issu", "uncut", "shop", "januari", "171", "white", "stuff", "2", "year", "dog", "3", "purpl", "audac", "2", "4", "suburban", "junki", "ladi", "5", "show", "tag", "6", "use", "7", "sic", "em", "slow", "8", "day", "swan", "9", "whopper", "dave", "10", "purpl", "audac", "1", "11", "icesubscrib", "uncut", "make", "huge", "save", "cover", "price", "click", "herelik", "facebook", "date", "latest", "news", "uncutth", "march", "2019", "issu", "uncut", "sale", "uk", "new", "order", "cover", "insid", "youll", "pete", "shelley", "rip", "massiv", "2019", "album", "preview", "sharon", "van", "etten", "mark", "knopfler", "paul", "simonon", "john", "martyn", "steve", "gunn", "15track", "cd", "showcas", "best", "month", "new", "music", "includ", "bruce", "springsteen", "william", "tyler", "dream", "syndicateuncut", "past", "present", "futur", "great", "music"], "date_published": ["2019-01-08T11:04:36+00:00", "2019-01-08T11:04:36+00:00"], "sentiment": 0.047558922558922564, "content": "After reforming in 2015, Royal Trux have announced their first album of new material since 2000.White Stuff will be released by Fat Possum on March 1, and you can hear the title track below:Order the latest issue of Uncut online and have it sent to your home!\u201cNothing has changed within the Truxian universe we created for ourselves as teenagers because Trux is and will always be our way of life whether living it together or separate,\u201d says the band\u2019s Jennifer Herrema. \u201cThis is no hobby rock kick. We are long game lifers with no fear, no regrets and plenty of gratitude for the way the universe has rewarded our singular dynamic.\u201dCheck out the White Stuff tracklisting below \u2013 and look out for a review in the next issue of Uncut, in shops on January 17.1. White Stuff\n2. Year Of The Dog\n3. Purple Audacity #2\n4. Suburban Junky Lady\n5. Shows And Tags\n6. Get Used To This\n7. Sic Em Slow\n8. Every Day Swan\n9. Whopper Dave\n10. Purple Audacity #1\n11. Under IceSubscribe to Uncut and make huge savings on the cover price \u2013 find out by clicking here!Like us on Facebook to keep up to date with the latest news from Uncut.The March 2019 issue of Uncut is now on sale in the UK \u2013 with New Order on the cover. Inside, you\u2019ll find Pete Shelley (RIP), our massive 2019 albums preview, Sharon Van Etten, Mark Knopfler, Paul Simonon, John Martyn, Steve Gunn and much more. Our 15-track CD also showcases the best of the month\u2019s new music, including Bruce Springsteen, William Tyler and the Dream Syndicate.Uncut: the past, present and future of great music.", "pptitle": ["hear", "titl", "track", "royal", "trux", "new", "album", "white", "stuff", "uncut"]}