{"id": "UN_146", "url": "https://www.uncut.co.uk/news/small-faces-wanted-make-heavier-stuff-107941", "name": ["Small", "Faces:", "\"We", "wanted", "to", "make", "heavier", "stuff\"", "-", "Uncut"], "description": ["current", "issu", "uncut", "shop", "avail", "order", "onlin", "click", "tell", "stori", "small", "face", "play", "psychedel", "1968", "album", "ogden", "nut", "gone", "flake", "band", "crown", "glori", "album", "hasten", "demiseinspir", "lsd", "sufi", "messag", "boat", "trip", "berkshir", "ogden", "small", "face", "explor", "numer", "world", "soul", "influenc", "afterglow", "psychpop", "whimsi", "journey", "spiritu", "explor", "song", "baker", "rene", "happydaystoytown", "lazi", "sunday", "brought", "music", "hall", "qualiti", "psychedel", "rock", "drummer", "kenney", "jone", "instig", "titl", "track", "distort", "instrument", "lp", "titl", "inspir", "come", "song", "say", "write", "melodi", "hum", "tune", "band", "wrote", "songord", "latest", "issu", "uncut", "onlin", "sent", "homebut", "ogden", "uniqu", "second", "care", "link", "suit", "song", "told", "stori", "happi", "stan", "meet", "variou", "insect", "search", "moon", "song", "connect", "gobbledygook", "narr", "stanley", "unwin", "took", "band", "catchphras", "convert", "strang", "languag", "happi", "stan", "inspir", "kenney", "jone", "want", "make", "anim", "film", "conclud", "began", "session", "olymp", "end", "record", "went", "ronni", "mac", "deep", "convers", "said", "make", "great", "cartoon", "say", "look", "second", "just", "carri", "talk", "like", "fuck", "know", "got", "eventuallyso", "went", "wrong", "turn", "point", "counterintuit", "choic", "singl", "launch", "album", "instead", "song", "repres", "album", "psychedel", "intent", "immedi", "releas", "lazi", "sunday", "hit", "nonetheless", "rankl", "band", "want", "make", "heavier", "stuff", "wed", "great", "album", "rinkydink", "thing", "chart", "say", "jone", "like", "song", "fuck", "stand", "like", "small", "face", "histori", "song", "get", "andrew", "loog", "oldham", "boss", "immedi", "label", "habit", "go", "olymp", "studio", "away", "pictur", "green", "mohair", "suit", "look", "fuck", "great", "genuin", "ask", "glyn", "john", "produc", "listen", "wed", "doingaccord", "jone", "realis", "lazi", "sunday", "releas", "marriott", "saw", "chart", "music", "paper", "nail", "coffin", "desper", "tri", "lose", "imag", "awar", "beatl", "do", "felt", "song", "like", "lazi", "sunday", "push", "backward", "got", "steve", "didnt", "realis", "get", "put", "band", "felt", "hed", "away", "imag", "unless", "got", "away", "bandjon", "nonpluss", "band", "dissolv", "precis", "bask", "success", "acclaim", "lp", "got", "insist", "steve", "brought", "rotten", "end", "walk", "offstag", "explain", "hed", "away", "wish", "hed", "talk", "timeread", "make", "small", "face", "ogden", "nut", "gone", "flake", "latest", "issu", "uncut", "bob", "dylan", "coversubscrib", "uncut", "make", "huge", "save", "cover", "price", "click", "herelik", "facebook", "date", "latest", "news", "uncutth", "decemb", "2018", "issu", "uncut", "sale", "uk", "bob", "dylan", "cover", "issu", "come", "uniqu", "12track", "bob", "dylan", "cd", "best", "bootleg", "seri", "featur", "exclus", "track", "dylan", "latest", "boxset", "issu", "youll", "exclus", "featur", "small", "face", "jeff", "tweedi", "psychedel", "fur", "mose", "sumney", "sister", "sledg", "jeff", "goldblum", "mariann", "fathful", "ty", "segal", "roger", "daltrey", "klau", "voormann", "moreuncut", "past", "present", "futur", "great", "music"], "date_published": ["2018-10-26T10:08:43+00:00", "2018-10-26T10:08:43+00:00"], "sentiment": 0.09575892857142855, "pptitle": ["small", "face", "want", "make", "heavier", "stuff", "uncut"]}