{"id": "PF_56", "url": "https://pitchfork.com/reviews/albums/dababy-baby-on-baby/", "name": ["Baby", "On", "Baby"], "description": ["13", "song", "dababi", "interscop", "debut", "babi", "babi", "13", "song", "start", "rap", "follow", "timestamp", "000", "007", "008", "016", "000", "000", "001", "000", "000", "002", "002", "006", "011", "fundament", "appeal", "dababi", "musicit", "aggress", "energet", "obsess", "forward", "motion", "charlott", "nativ", "turn", "color", "phrase", "sell", "rote", "one", "sheer", "charisma", "moodi", "beat", "shift", "lofti", "gestur", "dababi", "tri", "play", "museum", "brunch", "27yearold", "shirk", "onrecord", "gimmickri", "embrac", "promot", "famous", "pop", "street", "austin", "wear", "diaper", "sxsw", "2017", "shortli", "hed", "chang", "babi", "jesu", "recent", "music", "video", "funnier", "weirder", "viral", "there", "song", "dababi", "get", "pull", "hotbox", "car", "get", "head", "passeng", "placat", "cop", "tell", "check", "dababi", "appl", "music", "there", "breakout", "hit", "walker", "texa", "ranger", "dababi", "swerv", "mountain", "dodg", "ram", "watch", "twerk", "video", "iphon", "wheel", "there", "mini", "van", "collabor", "memphi", "rapper", "blocboy", "jb", "turn", "titular", "vehicl", "headquart", "pleasantseem", "crime", "syndic", "just", "yesterday", "drop", "clip", "suge", "yea", "yea", "imperson", "death", "row", "ceo", "complet", "muscl", "suit", "comic", "larg", "cigar", "crook", "mailman", "say", "dababi", "music", "written", "simpl", "joke", "song", "like", "rich", "homi", "quanassist", "celebrateor", "earlier", "song", "like", "tearsar", "undergird", "betray", "grim", "stake", "there", "matter", "fatal", "shoot", "huntersvil", "north", "carolina", "walmart", "fall", "left", "19yearold", "man", "dead", "dababi", "say", "shop", "children", "mother", "man", "attempt", "rob", "charg", "crime", "dababi", "funni", "sure", "dead", "brief", "moment", "remind", "dababi", "exist", "contemporari", "rap", "landscap", "album", "penultim", "song", "backend", "veer", "closer", "melod", "lightli", "autotun", "singsong", "domin", "rap", "radio", "decad", "doe", "usual", "gruff", "cadenc", "best", "friend", "appear", "remix", "featur", "rich", "kid", "interpol", "late", "xxxtentacion", "sad", "babi", "clear", "precis", "staccato", "athlet", "rapper", "whip", "song", "frenzi", "sheer", "forc", "babi", "babi", "come", "middl", "prolif", "period", "rapper", "mixtap", "babi", "talk", "5", "blank", "blank", "releas", "june", "novemb", "year", "respect", "underscor", "region", "popular", "nation", "crossov", "potenti", "dababi", "interview", "ambiti", "video", "commit", "fame", "thing", "music", "refreshingli", "pretens", "artific", "concern", "way", "play", "boardroom", "way", "play", "trunk"], "date_published": ["2019-03-08T06:00:00"], "sentiment": 0.09057352500748728, "pptitle": ["babi", "babi"]}