{"id": "RS_100", "url": "https://www.rollingstone.com/music/music-album-reviews/joji-ballads-1-review-746844/", "name": ["Review:", "Joji", "Releases", "Full-Length", "Debut,", "\u2018Ballads", "1\u2019", "\u2013", "Rolling", "Stone"], "description": ["know", "georg", "miller", "primarili", "shockcomedi", "expert", "help", "make", "baauer", "harlem", "shake", "viral", "seri", "pueril", "hip", "thrust", "2013", "new", "album", "joji", "evid", "greatest", "transform", "modern", "pop", "cultur", "ballad", "1", "elegiac", "prettili", "poutfac", "miller", "use", "make", "cring", "joji", "make", "like", "transform", "wasnt", "immedi", "miller", "start", "put", "music", "2014", "initi", "pink", "guy", "traffick", "rap", "stuck", "close", "outrag", "clicktast", "video", "filthi", "frank", "soon", "began", "releas", "medit", "melod", "song", "settl", "joji", "2017", "joji", "tongu", "bruis", "sensit", "onenot", "ep", "issu", "offici", "statement", "end", "filthi", "frank", "tongu", "felt", "like", "song", "day", "hear", "dour", "ballad", "gloom", "unvari", "drum", "program", "caus", "anguish", "process", "singer", "glum", "lyric", "ep", "show", "joji", "mainstream", "ambit", "he", "attun", "pop", "prevail", "wind", "ballad", "1", "track", "like", "test", "drive", "play", "entir", "catalog", "6lack", "halsey", "billi", "eilish", "bitch", "broken", "heart", "annuel", "aa", "brindemo", "lil", "wayn", "bat", "eye", "sound", "doesnt", "mean", "joji", "do", "fact", "appear", "master", "particular", "kind", "selfdeprec", "pop", "reason", "complet", "wail", "slow", "danc", "dark", "decid", "cut", "loss", "bow", "discuss", "compet", "overli", "chirpi", "announc", "dont", "social", "cue", "long", "nearli", "sadist", "want", "u", "punish", "im", "hang", "noos", "tiresom", "joji", "chang", "music", "approach", "time", "throw", "angsti", "guitar", "bash", "la", "east", "coaster", "respond", "winter", "want", "u", "entir", "convinc", "power", "ballad", "eighti", "tradit", "histrion", "solo", "album", "end", "bunch", "soft", "strum", "selfindulg", "pretti", "hardtodiscern", "autotun", "sing", "thing", "world", "away", "harlem", "shake", "video", "say", "peopl", "chang"], "date_published": ["2018-10-29T20:47:58+00:00"], "sentiment": 0.047760695187165775, "pptitle": ["review", "joji", "releas", "fulllength", "debut", "ballad", "1", "roll", "stone"]}