{"id": "UN_180", "url": "https://www.uncut.co.uk/news/queens-bohemian-rhapsody-soundtrack-feature-live-aid-songs-107133", "name": ["Queen's", "Bohemian", "Rhapsody", "soundtrack", "to", "feature", "Live", "Aid", "songs", "-", "Uncut"], "description": ["queen", "reveal", "detail", "soundtrack", "album", "releas", "octob", "19", "accompani", "upcom", "biopic", "bohemian", "rhapsodyit", "includ", "song", "histor", "1985", "live", "aid", "perform", "previous", "issu", "audio", "form", "22track", "album", "featur", "previous", "unreleas", "live", "track", "queen", "career", "brand", "new", "version", "old", "favouritesord", "latest", "issu", "uncut", "onlin", "sent", "home", "deliveri", "chargew", "rock", "start", "studio", "version", "seamlessli", "blend", "live", "perform", "audienc", "particip", "dont", "stop", "featur", "brian", "may", "newli", "record", "guitar", "part", "closer", "band", "play", "track", "live", "today", "do", "right", "origin", "record", "smile", "predecessor", "band", "queen", "featur", "brian", "roger", "vocalist", "tim", "staffel", "freddi", "mercuri", "interpret", "song", "featur", "queen", "album", "recreat", "origin", "smile", "version", "brian", "roger", "reunit", "staffel", "abbey", "road", "studioscheck", "tracklist", "bohemian", "rhapsodi", "soundtrack", "below1", "20th", "centuri", "fox", "fanfar", "025", "2", "somebodi", "love", "456", "3", "do", "right", "revisit", "perform", "smile", "317", "4", "aliv", "live", "rainbow", "356", "5", "killer", "queen", "259", "6", "fat", "bottom", "girl", "live", "pari", "438", "7", "bohemian", "rhapsodi", "555", "8", "im", "live", "hammersmith", "odeon", "426", "9", "crazi", "littl", "thing", "call", "love", "243", "10", "love", "life", "rock", "rio", "429", "11", "rock", "movi", "mix", "209", "12", "bite", "dust", "335", "13", "want", "break", "free", "343", "14", "pressur", "perform", "queen", "david", "bowi", "404", "15", "want", "live", "forev", "515", "16", "bohemian", "rhapsodi", "live", "aid", "228", "17", "radio", "ga", "ga", "live", "aid", "406", "18", "ayoh", "live", "aid", "041", "19", "hammer", "fall", "live", "aid", "404", "20", "champion", "live", "aid", "357", "21", "dont", "stop", "revisit", "338", "22", "432subscrib", "uncut", "make", "huge", "save", "cover", "price", "click", "herelik", "facebook", "date", "latest", "news", "uncutth", "octob", "2018", "issu", "uncut", "sale", "uk", "jimi", "hendrix", "cover", "issu", "youll", "exclus", "featur", "spiritu", "aretha", "franklin", "richard", "thompson", "soft", "cell", "pink", "floyd", "candi", "staton", "garcia", "peopl", "beach", "boy", "mudhoney", "big", "red", "machin", "free", "cd", "showcas", "15", "track", "month", "best", "new", "music", "includ", "beak", "low", "christin", "queen", "marissa", "nadler", "eric", "bachmanuncut", "past", "present", "futur", "great", "music"], "date_published": ["2018-09-05T15:05:03+00:00", "2018-09-05T15:05:03+00:00"], "sentiment": 0.15404424810162523, "pptitle": ["queen", "bohemian", "rhapsodi", "soundtrack", "featur", "live", "aid", "song", "uncut"]}