{"id": "NME_123", "url": "https://www.nme.com/news/music/looks-like-jeff-goldblum-playing-glastonbury-2019-2461164", "name": ["It", "looks", "like", "Jeff", "Goldblum", "could", "be", "playing", "Glastonbury", "2019\u2026"], "description": ["sing", "jurass", "park", "theme", "tuneit", "appear", "jeff", "goldblum", "orchestra", "set", "make", "appear", "perform", "glastonburi", "festiv", "2019star", "jurass", "park", "fli", "grand", "budapest", "hotel", "goldblum", "acclaim", "jazz", "musician", "year", "mildr", "snitzer", "orchestra", "releas", "acclaim", "debut", "album", "capitol", "studio", "sessionsaft", "number", "intim", "show", "look", "like", "goldblum", "set", "make", "music", "return", "uk", "hallow", "ground", "worthi", "farm", "john", "stori", "guitarist", "orchestra", "glastonburi", "music", "festiv", "list", "world", "tour", "date", "websit", "sunday", "june", "30nme", "approach", "spokesperson", "goldblum", "respons", "recent", "london", "landmark", "25foot", "inflat", "jeff", "goldblum", "statu", "erect", "site", "resal", "date", "ticket", "glastonburi", "2019", "confirm", "month", "lineup", "expect", "announc", "come", "weeksamong", "2019", "glastonburi", "rumour", "liam", "gallagh", "strongli", "tip", "make", "pyramid", "stage", "appear", "asid", "lizzo", "recent", "tell", "nme", "shed", "perform", "far", "kyli", "minogu", "confirm", "sunday", "legend", "slot", "janel", "mona", "reveal", "headlin", "west", "holt", "stage", "stormzi", "pyramid", "stage", "headlin", "announc", "farth", "cure", "killer", "current", "booki", "favourit", "main", "headlin", "interpol", "stereophon", "lana", "del", "rey", "childish", "gambino", "rumour", "performit", "recent", "confirm", "prodigi", "book", "play", "prior", "frontman", "keith", "flint", "tragic", "death"], "date_published": ["2019-03-13T14:21:25+00:00"], "sentiment": 0.1159722222222222, "pptitle": ["look", "like", "jeff", "goldblum", "play", "glastonburi", "2019"]}