{"id": "PF_75", "url": "https://pitchfork.com/reviews/albums/cochemea-all-my-relations/", "name": ["All", "My", "Relations"], "description": ["cochemea", "gastelum", "idea", "record", "relat", "saxophon", "player", "tour", "soul", "singer", "sharon", "jone", "pass", "away", "2016", "show", "46yearold", "gastelum", "rest", "jone", "back", "band", "dapk", "hit", "local", "record", "store", "host", "impromptu", "listen", "parti", "turntabl", "tour", "bu", "point", "afrocuban", "jazz", "player", "sabu", "martinez", "afro", "templ", "1973", "album", "combin", "rich", "layer", "latin", "percuss", "wail", "sax", "line", "hear", "record", "gastelumwho", "grew", "california", "live", "woodstock", "claim", "yaqui", "mescalero", "apach", "indian", "rootsfelt", "express", "feel", "ancestr", "background", "similar", "templat", "saxophon", "set", "wave", "percuss", "bewitch", "combin", "forg", "relat", "jazz", "album", "that", "equal", "part", "spiritu", "journey", "irrepress", "funk", "album", "10", "song", "mix", "improvis", "percuss", "impressionist", "melodi", "gastelum", "call", "group", "10", "musician", "engag", "collect", "write", "session", "dapton", "hous", "soul", "studio", "brooklyn", "theyd", "jam", "hit", "groov", "felt", "song", "start", "shape", "core", "ensembl", "featur", "percuss", "section", "built", "spellbind", "array", "conga", "bongo", "tabla", "dhol", "sheker", "rhythmic", "foundat", "embellish", "gastelum", "consumm", "saxophon", "play", "plu", "bass", "courtesi", "bosco", "mann", "clavinet", "pianet", "victor", "axelrod", "open", "song", "maso", "yeem", "encapsul", "blend", "sinewi", "smolder", "melodi", "line", "play", "smartli", "morph", "percuss", "build", "frantic", "climax", "mitot", "spearhead", "tight", "upbeat", "horn", "riff", "bring", "mind", "jame", "brown", "band", "jb", "seyewailo", "coast", "breezi", "bliss", "swing", "titl", "track", "defiant", "march", "includ", "commun", "chant", "aint", "gonna", "build", "wall", "relat", "boast", "syncop", "charm", "stem", "freedom", "groov", "inher", "jam", "session", "album", "spiritu", "elev", "come", "gastelum", "songwrit", "process", "take", "time", "consid", "relationship", "ancestr", "root", "attempt", "transform", "imag", "head", "melod", "phrase", "sonora", "name", "homeland", "gastelum", "ancestor", "prompt", "imagin", "place", "hed", "visit", "felt", "intens", "long", "track", "take", "beauti", "lonesom", "qualiti", "wist", "sax", "back", "strippeddown", "metronom", "percuss", "captur", "feel", "wander", "strang", "land", "theme", "ancestri", "spiritu", "connect", "add", "narr", "cohes", "album", "sonora", "follow", "ghostlysound", "interlud", "lo", "muerto", "give", "way", "mexican", "rhythm", "mescalero", "song", "written", "homag", "gastelum", "mescalero", "apach", "grandmoth", "gastelum", "deftli", "switch", "sax", "flute", "gastelum", "act", "grappl", "heritag", "translat", "heavi", "listen", "experi", "album", "end", "tranquil", "note", "inspir", "navajo", "song", "sh", "naash", "close", "song", "happi", "combin", "lilt", "percuss", "sort", "sweet", "soul", "refrain", "youd", "happili", "believ", "pen", "stevi", "wonder", "follow", "gravita", "what", "come", "finish", "usher", "feel", "seren", "gastelum", "discov", "end", "long", "journey", "past", "sens", "hope", "futur", "reward"], "date_published": ["2019-03-01T06:00:00"], "sentiment": 0.21645408163265306, "pptitle": ["relat"]}