{"id": "RS_131", "url": "https://www.rollingstone.com/music/music-album-reviews/review-lady-gaga-and-bradley-cooper-shine-bright-on-the-a-star-is-born-soundtrack-733184/", "name": ["Review:", "Lady", "Gaga", "and", "Bradley", "Cooper", "Shine", "Bright", "on", "the", "\u2018A", "Star", "Is", "Born\u2019", "Soundtrack", "\u2013", "Rolling", "Stone"], "description": ["star", "born", "minut", "your", "star", "born", "franchis", "your", "born", "roughli", "2040", "year", "differ", "icon", "center", "time", "ladi", "gaga", "pop", "chameleon", "have", "live", "seemingli", "thousand", "differ", "live", "10", "year", "burst", "scene", "street", "smart", "talent", "undervalu", "alli", "voic", "bigger", "bedroom", "dad", "hous", "live", "bigger", "restaur", "job", "loath", "bigger", "cramp", "drag", "bar", "she", "allow", "perform", "bigger", "small", "frame", "look", "diminut", "bradley", "cooper", "troubl", "rock", "star", "jackson", "main", "point", "star", "born", "alli", "life", "grow", "match", "talent", "progress", "song", "film", "lack", "confid", "sing", "song", "written", "goe", "classic", "like", "rainbow", "la", "vie", "en", "rose", "jackson", "open", "potenti", "move", "stage", "amphitheat", "play", "sing", "grandios", "power", "ballad", "like", "otherworldli", "mark", "ronsonassist", "highlight", "shallow", "explos", "rememb", "way", "song", "earli", "portion", "movi", "impenetr", "perfect", "gaga", "cooper", "lead", "write", "song", "album", "luka", "nelson", "gaga", "help", "cooper", "bluesinflect", "countryrock", "soul", "jackson", "main", "gritti", "downhom", "lyric", "propel", "nelsonl", "band", "back", "main", "stage", "cooper", "voic", "lower", "film", "creat", "worldweari", "addictionaddl", "main", "surprisingli", "great", "crackl", "like", "pit", "begin", "holler", "settl", "warm", "smoki", "rasp", "ballad", "time", "tast", "just", "talent", "main", "cooper", "perform", "acoust", "ballad", "mayb", "time", "drag", "bar", "meet", "alli", "kill", "time", "wait", "clean", "makeup", "hair", "paint", "jason", "isbel", "wrote", "sullen", "triumph", "song", "cooper", "deliv", "devast", "resign", "come", "grasp", "just", "lost", "main", "actual", "follow", "cover", "shallow", "time", "hear", "alli", "origin", "note", "trailer", "immedi", "captur", "world", "attent", "earthshak", "record", "moment", "arriv", "feel", "earn", "like", "time", "actual", "see", "alli", "music", "gaga", "help", "write", "stretch", "alli", "career", "she", "brunett", "perform", "man", "fall", "love", "gorgeou", "romant", "trite", "power", "feel", "like", "shouldv", "templat", "aim", "joann", "recent", "album", "design", "countrypop", "backtoherroot", "moment", "movi", "album", "progress", "focu", "alli", "right", "scout", "manag", "tour", "jackson", "excel", "pianobop", "look", "launch", "seri", "pop", "singl", "catchi", "wonder", "fameadjac", "execut", "song", "place", "film", "pop", "music", "world", "vapid", "soulcrush", "theyr", "written", "21st", "centuri", "trailblaz", "star", "suppos", "underscor", "idea", "alli", "lose", "write", "voic", "theyr", "delici", "fun", "shock", "pop", "nosed", "saturday", "night", "live", "perform", "dian", "warren", "copen", "did", "meant", "slightli", "ridicul", "highlight", "moment", "easi", "heavi", "love", "song", "incarn", "star", "born", "take", "surviv", "tragedi", "turn", "lead", "star", "climact", "moment", "alli", "take", "stage", "time", "song", "written", "husband", "ill", "love", "actual", "gaga", "special", "soul", "moment", "closer", "belt", "la", "vie", "en", "rose", "bar", "song", "sang", "tour", "jackson", "orangehair", "pop", "star", "she", "compos", "cri", "gown", "orchestra", "face", "stoic", "audienc", "assum", "time", "ill", "love", "meant", "biggest", "moment", "seri", "big", "moment", "feel", "earn", "time", "alli", "sang", "origin", "song", "audienc", "filmvers", "song", "switch", "sound", "jackson", "sing", "alli", "home", "time", "that", "classic", "star", "birth"], "date_published": ["2018-10-05T15:36:52+00:00"], "sentiment": 0.16274432638069003, "pptitle": ["review", "ladi", "gaga", "bradley", "cooper", "shine", "bright", "star", "born", "soundtrack", "roll", "stone"]}