{"id": "TG_39", "url": "https://www.theguardian.com/music/2019/feb/21/bernard-rands-chains-like-the-sea-cello-concerto-danza-petrificada-review-rare-but-never-rarified", "name": ["Bernard", "Rands:", "Chains", "Like", "the", "Sea;", "Danza", "Petrificada", "review", "|", "Andrew", "Clements'", "classical", "CD", "of", "the", "week", "|", "Music", "|", "The", "Guardian"], "description": ["nmc", "celebr", "30th", "birthday", "month", "launch", "modest", "cassettebas", "oper", "came", "new", "music", "cassett", "gone", "britain", "lead", "contemporari", "music", "label", "catalogu", "includ", "record", "signific", "british", "work", "time", "harrison", "birtwistl", "mask", "orpheu", "judith", "weir", "night", "chines", "opera", "benedict", "mason", "lighthous", "england", "wale", "tansi", "daviess", "spine", "nmc", "assidu", "promot", "upandcom", "compos", "typic", "bundl", "spring", "releas", "mark", "anniversari", "rang", "right", "age", "spectrum", "british", "music", "senior", "figur", "brightest", "new", "talent", "bernard", "rand", "85", "year", "automat", "consid", "british", "compos", "move", "unit", "state", "1975", "citizen", "year", "later", "flurri", "activ", "festiv", "rncm", "manchest", "prom", "commiss", "time", "80th", "birthday", "2014", "perform", "music", "britain", "rare", "record", "collect", "stem", "manchest", "event", "year", "ago", "provid", "strike", "proof", "vivid", "rand", "orchestr", "write", "influenc", "european", "studi", "1950", "teacher", "includ", "maderna", "berio", "dallapiccola", "supersed", "gestur", "style", "ear", "strike", "instrument", "effect", "assur", "2010", "concert", "open", "danza", "petrificada", "recent", "work", "constantli", "chang", "direct", "halo", "latin", "american", "percuss", "cello", "concerto", "compos", "mstislav", "rostropovich", "1996", "earliest", "outer", "movement", "base", "welsh", "folk", "song", "centrepiec", "rapt", "hymnlik", "cello", "line", "rand", "undergradu", "bangor", "welsh", "connect", "wonder", "suppl", "twomov", "chain", "like", "sea", "borrow", "titl", "dylan", "thoma", "mere", "programmat", "facebook", "twitter", "pinterest", "edmund", "finni", "latest", "issu", "nmc", "debut", "seri", "air", "turn", "strike", "collect", "work", "edmund", "finni", "born", "1984", "pupil", "julian", "anderson", "orchestr", "music", "play", "bbc", "scottish", "symphoni", "ilan", "volkov", "ensembl", "piec", "bcmg", "britten", "sinfonia", "solo", "piec", "show", "fastidi", "finni", "construct", "music", "cannili", "select", "adapt", "music", "model", "reveal", "preciou", "abil", "transform", "straightforward", "music", "object", "singl", "chord", "richli", "mysteri", "compel", "topic", "classic", "music", "album", "review", "share", "facebook", "share", "twitter", "share", "email", "share", "linkedin", "share", "pinterest", "share", "whatsapp", "share", "messeng", "reus", "content"], "date_published": ["2019-02-21T15:00:14+0000"], "sentiment": 0.19236617041495088, "pptitle": ["bernard", "rand", "chain", "like", "sea", "danza", "petrificada", "review", "andrew", "clement", "classic", "cd", "week", "music", "guardian"]}