{"id": "UN_15", "url": "https://www.uncut.co.uk/news/rolling-stones-announce-new-best-compilation-109832", "name": ["The", "Rolling", "Stones", "announce", "new", "'best", "of'", "compilation", "-", "Uncut"], "pptitle": ["roll", "stone", "announc", "new", "best", "compil", "uncut"], "description": ["roll", "stone", "announc", "new", "best", "compil", "call", "honk", "set", "releas", "polydor", "april", "19honk", "featur", "36", "band", "bestknown", "song", "1971", "onward", "delux", "edit", "3xcd", "4xlp", "includ", "bonu", "disc", "live", "track", "cull", "roll", "stone", "tour", "ventur", "career", "includ", "version", "cloud", "she", "rainbow", "wild", "hors", "featur", "florenc", "welch", "order", "latest", "issu", "uncut", "onlin", "sent", "homepreord", "honk", "perus", "tracklist", "3xcd", "delux", "edit", "belowdisc", "1", "start", "brown", "sugar", "rock", "miss", "tumbl", "dice", "just", "fool", "wild", "hors", "fool", "angi", "beast", "burden", "hot", "stuff", "rocknrol", "like", "rock", "hard", "place", "doom", "gloom", "love", "strong", "mix", "emot", "dont", "stop", "ride", "em", "disc", "2", "bitch", "harlem", "shuffl", "hate", "rough", "justic", "happi", "doo", "doo", "doo", "doo", "doo", "heartbreak", "shot", "respect", "got", "rock", "rain", "fall", "danc", "mr", "d", "undercov", "night", "emot", "rescu", "wait", "friend", "saint", "control", "street", "love", "tear", "disc", "3", "live", "track", "cloud", "danc", "mr", "d", "beast", "burden", "ed", "sheeran", "she", "rainbow", "wild", "hors", "florenc", "welch", "let", "spend", "night", "dead", "flower", "brad", "paisley", "shine", "light", "thumb", "bitch", "dave", "grohl", "subscrib", "uncut", "make", "huge", "save", "cover", "price", "click", "like", "facebook", "follow", "twitter", "date", "latest", "news", "uncutth", "april", "2019", "issu", "uncut", "sale", "uk", "john", "lennon", "cover", "insid", "youll", "keith", "richard", "ann", "brigg", "edwyn", "collin", "lou", "reed", "humbl", "pie", "robert", "forster", "jenni", "lewi", "jame", "brown", "15track", "cd", "showcas", "best", "month", "new", "music", "includ", "pond", "ex", "hex", "hand", "habit", "lambchop", "stephen", "malkmu", "kel", "assouf", "patti", "griffinuncut", "past", "present", "futur", "great", "music"], "date_published": ["2019-03-15T10:52:20+00:00"]}